{"settings":{"settings":{"wilcity_single_sidebar_my_text_field1580729157206":{"isCustomSection":"yes","icon":"","key":"wilcity_single_sidebar_my_text_field1580729157206","name":"Text Field","content":"[wilcity_render_input_field key={{my_text_field1580729157206}}]"},"businessHours":{"name":"Business Hours","key":"businessHours","icon":"la la-bookmark","status":"yes"},"priceRange":{"name":"Price Range","key":"priceRange","icon":"la la-bookmark","status":"yes"},"singlePrice":{"name":"Single Price","key":"singlePrice","icon":"la la-bookmark","status":"no"},"businessInfo":{"name":"Business Info","key":"businessInfo","icon":"la la-bookmark","status":"yes"},"statistic":{"name":"Statistic","key":"statistic","icon":"la la-bookmark","status":"yes"},"wilcity_single_sidebar_my_select_field1580714413925":{"isCustomSection":"yes","icon":"la la-bus","key":"wilcity_single_sidebar_my_select_field1580714413925","name":"Rental facts and features","content":"[wilcity_render_select_field key={{my_select_field1580714413925}} wrapper_classes={{col-sm-12 col-sm-12-clear}} title={{My Title}} description={{My description}}]","status":"yes"},"wilcity_single_sidebar_my_select_field1580638170362":{"isCustomSection":"yes","icon":"la la-home","key":"wilcity_single_sidebar_my_select_field1580638170362","name":"Amenities","content":"[wilcity_render_select_field key={{my_select_field1580638170362}} wrapper_classes={{col-sm-6 col-sm-6-clear}} title={{My Title}} description={{My description}}]"},"categories":{"name":"Categories","key":"categories","icon":"la la-bookmark","status":"yes"},"taxonomy":{"name":"Taxonomy","key":"taxonomy","icon":"la la-bookmark","isClone":"yes","taxonomy":"","status":"no"},"coupon":{"name":"Coupon","key":"coupon","icon":"la la-bookmark","status":"no"},"tags":{"name":"Tags","key":"tags","icon":"la la-bookmark","status":"yes"},"map":{"name":"Map","key":"map","icon":"la la-bookmark","status":"yes"},"author":{"name":"Author","key":"author","icon":"la la-user","status":"yes"},"claim":{"name":"Claim Listing","key":"claim","icon":"la la-bookmark","status":"yes"},"google_adsense":{"name":"Google AdSense","key":"google_adsense","icon":"la la-bullhorn","adminOnly":"yes","status":"yes"},"promotion_5e380418e7e55":{"promotionID":"","name":"Promotion","key":"promotion","style":"slider","icon":"la la-bullhorn","adminOnly":"yes","status":"yes","postsPerPage":"3","isMultipleSections":"yes"},"relatedListings_5e380418e7e5d":{"name":"Related Listings","key":"relatedListings","conditional":"listing_category","order":"DESC","style":"slider","orderby":"menu_order","oOrderFallbackBy":"post_date","icon":"la la-bullhorn","adminOnly":"yes","status":"yes","postsPerPage":"3","radius":"5","isMultipleSections":"yes"},"bookingcombannercreator":{"name":"Booking.com Banner Creator","key":"bookingcombannercreator","icon":"la la-hotel","status":"yes"},"myProducts":{"name":"My Products","key":"myProducts","icon":"la la-shopping-cart","status":"no"},"woocommerceBooking":{"name":"My Room","key":"woocommerceBooking","icon":"la la-shopping-cart","status":"no"}}},"postType":"renthouse","settingType":"single-sidebar"}
